agnostic/__init__.py
agnostic/cli.py
agnostic/mysql.py
agnostic/postgres.py
agnostic/sqlite.py
agnostic-1.0.3.dist-info/LICENSE
agnostic-1.0.3.dist-info/METADATA
agnostic-1.0.3.dist-info/WHEEL
agnostic-1.0.3.dist-info/entry_points.txt
agnostic-1.0.3.dist-info/RECORD
