Metadata-Version: 2.1
Name: agnostic
Version: 1.0.3
Summary: Agnostic Database Migrations
License: MIT
Author: Mark E. Haase
Author-email: mehaase@gmail.com
Requires-Python: >=3.8,<4.0
Classifier: License :: OSI Approved :: MIT License
Classifier: Programming Language :: Python :: 3
Classifier: Programming Language :: Python :: 3.8
Classifier: Programming Language :: Python :: 3.9
Classifier: Programming Language :: Python :: 3.10
Classifier: Programming Language :: Python :: 3.11
Requires-Dist: click (>=7.0)
Requires-Dist: pg8000[postgres] (>=1.30.1,<2.0.0)
Requires-Dist: pymysql[mysql] (>=1.1.0,<2.0.0)
Requires-Dist: sqlparse (>=0.2.4,<0.3.0)
